octobot_channels/__init__.pxd
octobot_channels/__init__.py
octobot_channels/constants.py
octobot_channels/consumer.c
octobot_channels/consumer.cp37-win_amd64.pyd
octobot_channels/consumer.pxd
octobot_channels/consumer.py
octobot_channels/producer.c
octobot_channels/producer.cp37-win_amd64.pyd
octobot_channels/producer.pxd
octobot_channels/producer.py
octobot_channels/channels/__init__.pxd
octobot_channels/channels/__init__.py
octobot_channels/channels/channel.c
octobot_channels/channels/channel.cp37-win_amd64.pyd
octobot_channels/channels/channel.pxd
octobot_channels/channels/channel.py
octobot_channels/channels/channel_instances.c
octobot_channels/channels/channel_instances.cp37-win_amd64.pyd
octobot_channels/channels/channel_instances.pxd
octobot_channels/channels/channel_instances.py
octobot_channels/util/__init__.pxd
octobot_channels/util/__init__.py
octobot_channels/util/channel_creator.c
octobot_channels/util/channel_creator.cp37-win_amd64.pyd
octobot_channels/util/channel_creator.pxd
octobot_channels/util/channel_creator.py
OctoBot_Channels-1.4.11.dist-info/LICENSE
OctoBot_Channels-1.4.11.dist-info/METADATA
OctoBot_Channels-1.4.11.dist-info/WHEEL
OctoBot_Channels-1.4.11.dist-info/top_level.txt
OctoBot_Channels-1.4.11.dist-info/RECORD
