Metadata-Version: 2.1
Name: OctoBot-Channels
Version: 1.4.11
Summary: OctoBot project channels module
Home-page: https://github.com/Drakkar-Software/OctoBot-Channels
Author: Drakkar-Software
Author-email: drakkar-software@protonmail.com
License: LGPL-3.0
Platform: UNKNOWN
Classifier: Development Status :: 5 - Production/Stable
Classifier: Operating System :: OS Independent
Classifier: Operating System :: MacOS :: MacOS X
Classifier: Operating System :: Microsoft :: Windows
Classifier: Operating System :: POSIX
Classifier: Programming Language :: Python :: 3.7
Classifier: Programming Language :: Cython
Classifier: Environment :: Console
Requires-Python: >=3.7
Requires-Dist: cython (==0.29.21)
Requires-Dist: OctoBot-Commons (<1.4,>=1.3.45)
